dophon_logger/__init__.py
dophon_logger/command.py
dophon_logger/dophon.py
dophon_logger/hues.py
dophon_logger-0.1.2.post7.dist-info/LICENSE
dophon_logger-0.1.2.post7.dist-info/WHEEL
dophon_logger-0.1.2.post7.dist-info/METADATA
dophon_logger-0.1.2.post7.dist-info/RECORD
