Metadata-Version: 2.1
Name: dophon-logger
Version: 0.1.2.post7
Summary: dophon logger module
Author: CallMeE
Author-email: ealohu@163.com
Requires-Python: >=3.6,<4.0
Classifier: Programming Language :: Python :: 3
Classifier: Programming Language :: Python :: 3.6
Classifier: Programming Language :: Python :: 3.7
Requires-Dist: hues (>=0.2.2,<0.3.0)
